financebuddy/__init__.py
financebuddy/cli.py
financebuddy/currencyutils.py
financebuddy/exceptions.py
financebuddy/export/__init__.py
financebuddy/export/api.py
financebuddy/export/factory.py
financebuddy/export/models.py
financebuddy/export/integrations/__init__.py
financebuddy/export/integrations/base.py
financebuddy/export/integrations/financebuddy_csv.py
financebuddy/export/integrations/financebuddy_json.py
financebuddy/parser/__init__.py
financebuddy/parser/api.py
financebuddy/parser/factory.py
financebuddy/parser/helpers.py
financebuddy/parser/integrations/__init__.py
financebuddy/parser/integrations/base.py
financebuddy/parser/integrations/csv.py
financebuddy/parser/integrations/dataframe.py
financebuddy/parser/integrations/excel.py
financebuddy/parserconfig/__init__.py
financebuddy/parserconfig/api.py
financebuddy/parserconfig/factory.py
financebuddy/parserconfig/models.py
financebuddy/parserconfig/integrations/__init__.py
financebuddy/parserconfig/integrations/csv.py
financebuddy/parserconfig/integrations/dataframe.py
financebuddy/parserconfig/integrations/excel.py
financebuddy/report/__init__.py
financebuddy/report/api.py
financebuddy/report/models.py
financebuddy-0.8.0.dist-info/METADATA
financebuddy-0.8.0.dist-info/WHEEL
financebuddy-0.8.0.dist-info/entry_points.txt
financebuddy-0.8.0.dist-info/licenses/LICENSE.md
financebuddy-0.8.0.dist-info/RECORD
