Metadata-Version: 2.3
Name: financebuddy
Version: 0.8.0
Summary: FinanceBuddy is a tool that centralizes and parses data from diffent banks into a unified format, streamlining the process for analytics and reporting.
Project-URL: Homepage, https://github.com/cedricduriau/financebuddy
Project-URL: Parsers, https://github.com/cedricduriau/financebuddy-parsers
Author-email: Cedric Duriau <duriau.cedric@live.be>
License-File: LICENSE.md
Requires-Python: >=3.12
Requires-Dist: babel>=2.16.0
Requires-Dist: financebuddy-parsers>=0.1.0
Requires-Dist: openpyxl>=3.1.5
Requires-Dist: pandas>=1.61
Requires-Dist: pycountry>=24.6.0
Requires-Dist: pydantic>=2.9.1
Requires-Dist: python-dateutil>=2.9.0
Requires-Dist: tabulate>=0.9.0
Provides-Extra: dev
Requires-Dist: freezegun>=1.5.0; extra == 'dev'
Requires-Dist: pip-tools>=6.12.0; extra == 'dev'
Requires-Dist: pytest-cov>=4.0.0; extra == 'dev'
Requires-Dist: pytest-freezegun>=0.4.0; extra == 'dev'
Requires-Dist: pytest>=7.3.1; extra == 'dev'
Requires-Dist: ruff>=0.0.290; extra == 'dev'
